LICENSE
README.md
setup.py
pandasio/__init__.py
pandasio.egg-info/PKG-INFO
pandasio.egg-info/SOURCES.txt
pandasio.egg-info/dependency_links.txt
pandasio.egg-info/requires.txt
pandasio.egg-info/top_level.txt