Metadata-Version: 2.1
Name: pandasio
Version: 0.0.4
Summary: Pandas to_sql/read_sql_query with primary/foreign key support
Home-page: https://github.com/EMeraldGeo/PandasIO
Author: Egil Moeller
Author-email: em@emeraldgeo.no
License: UNKNOWN
Platform: UNKNOWN
